{
  "original": {
    "total_samples": 12799,
    "classes": 34,
    "gini_coefficient": 0.6509952523864456,
    "imbalance_ratio": 1961.0,
    "min_samples": 1,
    "max_samples": 1961
  },
  "balanced": {
    "total_samples": 12898,
    "classes": 34,
    "gini_coefficient": 0.6431047221183404,
    "imbalance_ratio": 1961.0,
    "min_samples": 1,
    "max_samples": 1961
  },
  "improvement": {
    "added_samples": 99,
    "gini_reduction": 0.007890530268105267,
    "classes_improved": 5,
    "classes_needing_attention": 11
  }
}